{
  "warning_1755942120879_mrxRk_8": {
    "name": "warning_1755942120879_mrxRk_8",
    "x": -17,
    "y": 71,
    "z": 34,
    "owner": "mrxRk_8",
    "timestamp": 1755942120881,
    "world": "Singleplayer"
  },
  "warning_1755942139989_mrxRk_8": {
    "name": "warning_1755942139989_mrxRk_8",
    "x": 17,
    "y": 77,
    "z": 27,
    "owner": "mrxRk_8",
    "timestamp": 1755942139989,
    "world": "Singleplayer"
  },
  "warning_1755942146187_mrxRk_8": {
    "name": "warning_1755942146187_mrxRk_8",
    "x": -51,
    "y": 81,
    "z": 7,
    "owner": "mrxRk_8",
    "timestamp": 1755942146187,
    "world": "Singleplayer"
  },
  "warning_1755942151644_mrxRk_8": {
    "name": "warning_1755942151644_mrxRk_8",
    "x": -145,
    "y": 78,
    "z": 84,
    "owner": "mrxRk_8",
    "timestamp": 1755942151644,
    "world": "Singleplayer"
  }
}